__init__.py
abasepytest/__init__.py
abasepytest/base.py
pyarmor_runtime_000000/__init__.py
pyarmor_runtime_000000/pyarmor_runtime.pyd
abasepytest-0.0.1.dist-info/LICENSE
abasepytest-0.0.1.dist-info/METADATA
abasepytest-0.0.1.dist-info/WHEEL
abasepytest-0.0.1.dist-info/top_level.txt
abasepytest-0.0.1.dist-info/RECORD
