Metadata-Version: 2.1
Name: abasepytest
Version: 0.0.1
Requires-Python: <3.11
License-File: LICENSE
